networkx_robustness/__init__.py
networkx_robustness/networkx_robustness.py
networkx_robustness-0.0.6.dist-info/METADATA
networkx_robustness-0.0.6.dist-info/WHEEL
networkx_robustness-0.0.6.dist-info/licenses/LICENSE
networkx_robustness-0.0.6.dist-info/RECORD
