Metadata-Version: 2.1
Name: networkx_robustness
Version: 0.0.6
Summary: A package for simulating network attacks on NetworkX graphs
Project-URL: Homepage, https://github.com/tsantanam/networkx-robustness
Project-URL: Bug Tracker, https://github.com/tsantanam/networkx-robustness/issues
Author-email: Tejas Santanam <santanam.tejas@gmail.com>
License-File: LICENSE
Classifier: License :: OSI Approved :: MIT License
Classifier: Operating System :: OS Independent
Classifier: Programming Language :: Python :: 3
Requires-Python: >=3.7
